aliyunsdkdms_enterprise/__init__.py
aliyunsdkdms_enterprise/endpoint.py
aliyunsdkdms_enterprise/request/__init__.py
aliyunsdkdms_enterprise/request/v20181101/AddAuthorityTemplateItemsRequest.py
aliyunsdkdms_enterprise/request/v20181101/AddDesensitizationRuleRequest.py
aliyunsdkdms_enterprise/request/v20181101/AddInstanceRequest.py
aliyunsdkdms_enterprise/request/v20181101/AddLhMembersRequest.py
aliyunsdkdms_enterprise/request/v20181101/AddLogicTableRouteConfigRequest.py
aliyunsdkdms_enterprise/request/v20181101/AddTaskFlowEdgesRequest.py
aliyunsdkdms_enterprise/request/v20181101/AnalyzeSQLLineageRequest.py
aliyunsdkdms_enterprise/request/v20181101/ApproveOrderRequest.py
aliyunsdkdms_enterprise/request/v20181101/BackFillRequest.py
aliyunsdkdms_enterprise/request/v20181101/BuyPayAsYouGoOrderRequest.py
aliyunsdkdms_enterprise/request/v20181101/ChangeColumnSecLevelRequest.py
aliyunsdkdms_enterprise/request/v20181101/ChangeColumnSecurityLevelRequest.py
aliyunsdkdms_enterprise/request/v20181101/ChangeLhDagOwnerRequest.py
aliyunsdkdms_enterprise/request/v20181101/CloseOrderRequest.py
aliyunsdkdms_enterprise/request/v20181101/CreateAbacAuthorizationRequest.py
aliyunsdkdms_enterprise/request/v20181101/CreateAbacPolicyRequest.py
aliyunsdkdms_enterprise/request/v20181101/CreateAuthorityTemplateRequest.py
aliyunsdkdms_enterprise/request/v20181101/CreateDataArchiveOrderRequest.py
aliyunsdkdms_enterprise/request/v20181101/CreateDataCorrectOrderRequest.py
aliyunsdkdms_enterprise/request/v20181101/CreateDataCronClearOrderRequest.py
aliyunsdkdms_enterprise/request/v20181101/CreateDataExportOrderRequest.py
aliyunsdkdms_enterprise/request/v20181101/CreateDataImportOrderRequest.py
aliyunsdkdms_enterprise/request/v20181101/CreateDataTrackOrderRequest.py
aliyunsdkdms_enterprise/request/v20181101/CreateDatabaseExportOrderRequest.py
aliyunsdkdms_enterprise/request/v20181101/CreateFreeLockCorrectOrderRequest.py
aliyunsdkdms_enterprise/request/v20181101/CreateLakeHouseSpaceRequest.py
aliyun_python_sdk_dms_enterprise-1.53.12.dist-info/LICENSE
aliyun_python_sdk_dms_enterprise-1.53.12.dist-info/METADATA
aliyun_python_sdk_dms_enterprise-1.53.12.dist-info/WHEEL
aliyun_python_sdk_dms_enterprise-1.53.12.dist-info/top_level.txt
aliyun_python_sdk_dms_enterprise-1.53.12.dist-info/RECORD
